odoo/addons/shopinvader_customer_multi_user_wishlist/README.rst
odoo/addons/shopinvader_customer_multi_user_wishlist/__init__.py
odoo/addons/shopinvader_customer_multi_user_wishlist/__manifest__.py
odoo/addons/shopinvader_customer_multi_user_wishlist/components/__init__.py
odoo/addons/shopinvader_customer_multi_user_wishlist/components/access_info.py
odoo/addons/shopinvader_customer_multi_user_wishlist/i18n/shopinvader_customer_multi_user_wishlist.pot
odoo/addons/shopinvader_customer_multi_user_wishlist/readme/CONTRIBUTORS.rst
odoo/addons/shopinvader_customer_multi_user_wishlist/readme/CREDITS.rst
odoo/addons/shopinvader_customer_multi_user_wishlist/readme/DESCRIPTION.rst
odoo/addons/shopinvader_customer_multi_user_wishlist/services/__init__.py
odoo/addons/shopinvader_customer_multi_user_wishlist/services/wishlist.py
odoo/addons/shopinvader_customer_multi_user_wishlist/static/description/index.html
odoo/addons/shopinvader_customer_multi_user_wishlist/tests/__init__.py
odoo/addons/shopinvader_customer_multi_user_wishlist/tests/test_wishlist.py
odoo13_addon_shopinvader_customer_multi_user_wishlist-13.0.1.1.1.dist-info/METADATA
odoo13_addon_shopinvader_customer_multi_user_wishlist-13.0.1.1.1.dist-info/WHEEL
odoo13_addon_shopinvader_customer_multi_user_wishlist-13.0.1.1.1.dist-info/top_level.txt
odoo13_addon_shopinvader_customer_multi_user_wishlist-13.0.1.1.1.dist-info/RECORD
