Metadata-Version: 2.1
Name: odoo13-addon-shopinvader-customer-multi-user-wishlist
Version: 13.0.1.1.1
Summary: Integrate customer multi user and wishlist.
Home-page: https://github.com/shopinvader/odoo-shopinvader
Author: Camptocamp SA
License: AGPL-3
Platform: UNKNOWN
Classifier: Programming Language :: Python
Classifier: Framework :: Odoo
Classifier: License :: OSI Approved :: GNU Affero General Public License v3
Requires-Python: >=3.5
Requires-Dist: odoo13-addon-shopinvader-customer-multi-user
Requires-Dist: odoo13-addon-shopinvader-wishlist
Requires-Dist: odoo (<13.1dev,>=13.0a)
